deribit/__init__.py
deribit/auth.py
deribit/rest.py
deribit/ws.py
deribit_py-0.1.0.dist-info/METADATA
deribit_py-0.1.0.dist-info/WHEEL
deribit_py-0.1.0.dist-info/top_level.txt
deribit_py-0.1.0.dist-info/RECORD
