Metadata-Version: 2.4
Name: deribit-py
Version: 0.1.0
Summary: A complete async Python client for Deribit Options Market (REST & WebSocket)
Author-email: User <user@example.com>
Project-URL: Homepage, https://github.com/example/deribit-options-client
Classifier: Programming Language :: Python :: 3
Classifier: License :: OSI Approved :: MIT License
Classifier: Operating System :: OS Independent
Requires-Python: >=3.8
Requires-Dist: aiohttp>=3.8.0
Requires-Dist: websockets>=11.0
